pmakeup/TargetDescriptor.py
pmakeup/__init__.py
pmakeup/global_variables.py
pmakeup/main.py
pmakeup/version.py
pmakeup/cache/IPMakeupCache.py
pmakeup/cache/JsonPMakeupCache.py
pmakeup/cache/__init__.py
pmakeup/decorators/__init__.py
pmakeup/decorators/register_command.py
pmakeup/decorators/show_on_help.py
pmakeup/exceptions/AssertionPMakeupException.py
pmakeup/exceptions/InvalidScenarioPMakeupException.py
pmakeup/exceptions/PMakeupException.py
pmakeup/exceptions/__init__.py
pmakeup/git/GitPMakeupPlugin.py
pmakeup/git/__init__.py
pmakeup/models/AttrDict.py
pmakeup/models/PMakeupModel.py
pmakeup/models/PMakeupRegistry.py
pmakeup/models/__init__.py
pmakeup/models/commons_types.py
pmakeup/package_data/PMakeupfile.py.template
pmakeup/package_data/README.md.template
pmakeup/package_data/__init__.py.template
pmakeup/package_data/package-info.json
pmakeup/package_data/plugin_class.py.template
pmakeup/package_data/setup.py.template
pmakeup/package_data/test.py.template
pmakeup/platforms/IOSSystem.py
pmakeup/platforms/InterestingPath.py
pmakeup/platforms/LinuxOSSystem.py
pmakeup/platforms/WindowsOSSystem.py
pmakeup/platforms/__init__.py
pmakeup/plugins/AbstractPmakeupPlugin.py
pmakeup/plugins/__init__.py
pmakeup/plugins/cache/CachePMakeupPlugin.py
pmakeup/plugins/cache/__init__.py
pmakeup/plugins/core/CorePMakeupPlugin.py
pmakeup/plugins/core/__init__.py
pmakeup/plugins/files/FilesPMakeupPlugin.py
pmakeup/plugins/files/__init__.py
pmakeup/plugins/git/CommitEntry.py
pmakeup/plugins/git/GitPMakeupPlugin.py
pmakeup/plugins/git/__init__.py
pmakeup/plugins/linux/LinuxPMakeupPlugin.py
pmakeup/plugins/linux/__init__.py
pmakeup/plugins/log/LoggingPMakeupPlugin.py
pmakeup/plugins/log/__init__.py
pmakeup/plugins/operating_system/OperatingSystemPMakeupPlugin.py
pmakeup/plugins/operating_system/__init__.py
pmakeup/plugins/paths/PathsPMakeupPlugin.py
pmakeup/plugins/paths/__init__.py
pmakeup/plugins/strings/StringsPMakeupPlugin.py
pmakeup/plugins/strings/__init__.py
pmakeup-4.5.11.dist-info/LICENSE.md
pmakeup-4.5.11.dist-info/METADATA
pmakeup-4.5.11.dist-info/WHEEL
pmakeup-4.5.11.dist-info/entry_points.txt
pmakeup-4.5.11.dist-info/top_level.txt
pmakeup-4.5.11.dist-info/RECORD
