Metadata-Version: 2.1
Name: pmakeup
Version: 4.5.11
Summary: CLI utility for performing task Makefile-like
Home-page: https://github.com/Koldar/pmakeup.git
Author: Massimo Bono
Author-email: massimobono1@gmail.com
License: UNKNOWN
Platform: UNKNOWN
Classifier: Programming Language :: Python :: 3
Classifier: License :: OSI Approved :: MIT License
Classifier: Operating System :: OS Independent
Requires: setuptools
Requires: wheel
Requires-Python: >=3.6
Requires-Dist: alabaster (>=0.7.12)
Requires-Dist: archive-pmakeup-plugin (>=1.0.3)
Requires-Dist: colorama (>=0.4.4)
Requires-Dist: decorator (>=4.4.2)
Requires-Dist: networkx (>=2.5.1)
Requires-Dist: pmakeup (>=4.3.3)
Requires-Dist: psutil (>=5.8.0)
Requires-Dist: semantic-version (>=2.8.5)
Provides-Extra: doc
Provides-Extra: test
